plover_console_ui/__init__.py
plover_console_ui/add_translation.py
plover_console_ui/application.py
plover_console_ui/commander.py
plover_console_ui/commands.py
plover_console_ui/config.py
plover_console_ui/console_engine.py
plover_console_ui/dictionary_filter.py
plover_console_ui/focus.py
plover_console_ui/layout.py
plover_console_ui/notification.py
plover_console_ui/output.py
plover_console_ui/plugin.py
plover_console_ui/suggestions.py
plover_console_ui/tape.py
plover_console_ui-1.2.3.dist-info/LICENSE
plover_console_ui-1.2.3.dist-info/METADATA
plover_console_ui-1.2.3.dist-info/WHEEL
plover_console_ui-1.2.3.dist-info/entry_points.txt
plover_console_ui-1.2.3.dist-info/top_level.txt
plover_console_ui-1.2.3.dist-info/zip-safe
plover_console_ui-1.2.3.dist-info/RECORD
