Metadata-Version: 2.1
Name: plover-console-ui
Version: 1.2.3
Summary: Text User Interface for Plover
Home-page: https://github.com/psethwick/plover_console_ui
Author: Seth Rider
Author-email: seth.rider@gmail.com
License: GNU General Public License v3 or later (GPLv3+)
Keywords: plover plover_plugin cli
Classifier: Development Status :: 4 - Beta
Classifier: Environment :: Plugins
Classifier: Intended Audience :: End Users/Desktop
Classifier: License :: OSI Approved :: GNU General Public License v3 or later (GPLv3+)
Classifier: Operating System :: OS Independent
Classifier: Programming Language :: Python :: 3
License-File: LICENSE
